omc3/__init__.py
omc3/__main__.py
omc3/amplitude_detuning_analysis.py
omc3/check_corrections.py
omc3/global_correction.py
omc3/hole_in_one.py
omc3/kmod_importer.py
omc3/knob_extractor.py
omc3/madx_wrapper.py
omc3/model_creator.py
omc3/mqt_extractor.py
omc3/response_creator.py
omc3/sbs_propagation.py
omc3/tbt_converter.py
omc3/bin/madx-linux64-gnu
omc3/bin/madx-macosx64-gnu
omc3/bin/madx-win64-gnu.exe
omc3/bin/update_madx_from_afs.sh
omc3/correction/__init__.py
omc3/correction/arc_by_arc.py
omc3/correction/constants.py
omc3/correction/filters.py
omc3/correction/handler.py
omc3/correction/model_appenders.py
omc3/correction/model_diff.py
omc3/correction/response_io.py
omc3/correction/response_madng.py
omc3/correction/response_madx.py
omc3/correction/response_twiss.py
omc3/correction/sequence_evaluation.py
omc3/definitions/__init__.py
omc3/definitions/constants.py
omc3/definitions/formats.py
omc3/definitions/optics.py
omc3/harpy/__init__.py
omc3/harpy/clean.py
omc3/harpy/constants.py
omc3/harpy/frequency.py
omc3/harpy/handler.py
omc3/harpy/kicker.py
omc3/model/__init__.py
omc3/model/constants.py
omc3/model/manager.py
omc3/model/accelerators/__init__.py
omc3/model/accelerators/accelerator.py
omc3/model/accelerators/esrf.py
omc3/model/accelerators/generic.py
omc3/model/accelerators/iota.py
omc3/model/accelerators/lhc.py
omc3/model/accelerators/petra.py
omc3/model/accelerators/ps.py
omc3/model/accelerators/psbase.py
omc3/model/accelerators/psbooster.py
omc3/model/accelerators/skekb.py
omc3/model/accelerators/sps.py
omc3/model/accelerators/iota/lattice_main.madx
omc3/model/accelerators/iota/twiss.dat
omc3/model/accelerators/iota/twiss_elements.dat
omc3/model/accelerators/iota/include/OSC.madx
omc3/model/accelerators/iota/include/elements.madx
omc3/model/accelerators/iota/include/fields_1NL.dat
omc3/model/accelerators/iota/include/fields_2NL.dat
omc3/model/accelerators/iota/include/fields_EL.dat
omc3/model/accelerators/iota/include/fields_MM.dat
omc3-0.27.0.dist-info/METADATA
omc3-0.27.0.dist-info/WHEEL
omc3-0.27.0.dist-info/licenses/LICENSE
omc3-0.27.0.dist-info/RECORD
