Metadata-Version: 2.4
Name: omc3
Version: 0.27.0
Summary: An accelerator physics tools package for the OMC team at CERN.
Project-URL: homepage, https://github.com/pylhc/omc3
Project-URL: repository, https://github.com/pylhc/omc3
Project-URL: documentation, https://pylhc.github.io/omc3/
Project-URL: changelog, https://github.com/pylhc/omc3/blob/master/CHANGELOG.md
Author-email: OMC Team <pylhc@github.com>
License-Expression: MIT
License-File: LICENSE
Classifier: Intended Audience :: Science/Research
Classifier: License :: OSI Approved :: MIT License
Classifier: Natural Language :: English
Classifier: Operating System :: OS Independent
Classifier: Programming Language :: Python :: 3 :: Only
Classifier: Programming Language :: Python :: 3.10
Classifier: Programming Language :: Python :: 3.11
Classifier: Programming Language :: Python :: 3.12
Classifier: Programming Language :: Python :: 3.13
Classifier: Programming Language :: Python :: Implementation :: CPython
Classifier: Topic :: Scientific/Engineering
Classifier: Topic :: Scientific/Engineering :: Physics
Classifier: Topic :: Scientific/Engineering :: Visualization
Classifier: Topic :: Software Development :: Libraries :: Python Modules
Classifier: Typing :: Typed
Requires-Python: >=3.10
Requires-Dist: generic-parser>=1.1
Requires-Dist: h5py>=2.9
Requires-Dist: matplotlib>=3.8
Requires-Dist: numpy>=1.24
Requires-Dist: odrpack>=0.4.0
Requires-Dist: optics-functions>=0.1
Requires-Dist: pandas>=2.1
Requires-Dist: requests>=2.27
Requires-Dist: scikit-learn>=1.0
Requires-Dist: scipy>=1.10
Requires-Dist: sdds>=0.4
Requires-Dist: tables>=3.10.1
Requires-Dist: tfs-pandas>=3.8
Requires-Dist: turn-by-turn>=1.0
Provides-Extra: all
Requires-Dist: gitpython>=3.1; extra == 'all'
Requires-Dist: jpype1>=1.3; extra == 'all'
Requires-Dist: kerberos>=1.3.1; extra == 'all'
Requires-Dist: nxcals>=1.6.6; extra == 'all'
Requires-Dist: pylogbook>=3.4; extra == 'all'
Requires-Dist: pymadng>=0.8.3; extra == 'all'
Requires-Dist: pymupdf>=1.22; extra == 'all'
Requires-Dist: pyside2; extra == 'all'
Requires-Dist: pyspark>=3.5; extra == 'all'
Requires-Dist: pytest-cov>=2.9; extra == 'all'
Requires-Dist: pytest-timeout>=1.4; extra == 'all'
Requires-Dist: pytest>=7.0; extra == 'all'
Requires-Dist: pytimber>=3.0; extra == 'all'
Requires-Dist: qtpy>=2.3.1; extra == 'all'
Requires-Dist: sphinx-rtd-theme>=2.0; extra == 'all'
Requires-Dist: sphinx>=7.0; extra == 'all'
Provides-Extra: cern
Requires-Dist: jpype1>=1.3; extra == 'cern'
Requires-Dist: kerberos>=1.3.1; extra == 'cern'
Requires-Dist: nxcals>=1.6.6; extra == 'cern'
Requires-Dist: pylogbook>=3.4; extra == 'cern'
Requires-Dist: pyspark>=3.5; extra == 'cern'
Requires-Dist: pytimber>=3.0; extra == 'cern'
Provides-Extra: doc
Requires-Dist: sphinx-rtd-theme>=2.0; extra == 'doc'
Requires-Dist: sphinx>=7.0; extra == 'doc'
Provides-Extra: madng
Requires-Dist: pymadng>=0.8.3; extra == 'madng'
Provides-Extra: optional
Requires-Dist: pymupdf>=1.22; extra == 'optional'
Requires-Dist: pyside2; extra == 'optional'
Requires-Dist: qtpy>=2.3.1; extra == 'optional'
Provides-Extra: test
Requires-Dist: gitpython>=3.1; extra == 'test'
Requires-Dist: jpype1>=1.3; extra == 'test'
Requires-Dist: pymadng>=0.8.3; extra == 'test'
Requires-Dist: pytest-cov>=2.9; extra == 'test'
Requires-Dist: pytest-timeout>=1.4; extra == 'test'
Requires-Dist: pytest>=7.0; extra == 'test'
